{
  "collectionName": "components_budget_line_budget_lines",
  "info": {
    "name": "BudgetLine",
    "icon": "align-justify",
    "description": ""
  },
  "options": {},
  "attributes": {
    "concept": {
      "type": "string"
    },
    "quantity": {
      "type": "decimal"
    },
    "amount": {
      "type": "decimal"
    },
    "total_amount": {
      "type": "decimal"
    },
    "charged": {
      "type": "boolean",
      "default": false
    },
    "invoice": {
      "type": "string"
    }
  }
}
